app_store_connect_client/__init__.py
app_store_connect_client/analytics.py
app_store_connect_client/config.py
app_store_connect_client/dataclass.py
app_store_connect_client/exceptions.py
app_store_connect_client/log.py
app_store_connect_client/query.py
app_store_connect_client-2.0.4.dist-info/LICENSE
app_store_connect_client-2.0.4.dist-info/WHEEL
app_store_connect_client-2.0.4.dist-info/METADATA
app_store_connect_client-2.0.4.dist-info/RECORD
