Metadata-Version: 2.1
Name: app-store-connect-client
Version: 2.0.4
Summary: Python package for App Store connect Analytics.
Home-page: https://github.com/shmokmt
License: MIT
Author: shmokmt
Author-email: shoma.okamoto@fuller.co.jp
Requires-Python: >=3.6,<4.0
Classifier: License :: OSI Approved :: MIT License
Classifier: Programming Language :: Python :: 3
Classifier: Programming Language :: Python :: 3.6
Classifier: Programming Language :: Python :: 3.7
Classifier: Programming Language :: Python :: 3.8
Classifier: Topic :: Internet :: WWW/HTTP
Classifier: Topic :: Utilities
Requires-Dist: black (>=19.10b0,<20.0)
Requires-Dist: jsonschema (>=3.2.0,<4.0.0)
Requires-Dist: python-dateutil (>=2.8.1,<3.0.0)
Requires-Dist: python-dotenv (>=0.13.0,<0.14.0)
Requires-Dist: requests (>=2.23.0,<3.0.0)
Project-URL: Documentation, https://github.com/shmokmt/app-store-connect-client/wiki
Project-URL: Repository, https://github.com/shmokmt/app-store-connect-client
